QipianDeYishu/README.md
QipianDeYishu/__init__.py
QipianDeYishu/__main__.py
QipianDeYishu/file.epub
QipianDeYishu/index.html
QipianDeYishu/css/__init__.py
QipianDeYishu/css/annotations.css
QipianDeYishu/css/main.css
QipianDeYishu/css/normalize.css
QipianDeYishu/css/popup.css
QipianDeYishu/font/__init__.py
QipianDeYishu/font/fontello.eot
QipianDeYishu/font/fontello.svg
QipianDeYishu/font/fontello.ttf
QipianDeYishu/font/fontello.woff
QipianDeYishu/img/__init__.py
QipianDeYishu/img/annotator-glyph-sprite.png
QipianDeYishu/img/annotator-icon-sprite.png
QipianDeYishu/img/apple-touch-icon.png
QipianDeYishu/img/cancelfullscreen.png
QipianDeYishu/img/close.png
QipianDeYishu/img/fullscreen.png
QipianDeYishu/img/loader.gif
QipianDeYishu/img/menu-icon.png
QipianDeYishu/img/save.png
QipianDeYishu/img/saved.png
QipianDeYishu/img/settings-s.png
QipianDeYishu/img/settings.png
QipianDeYishu/img/star.png
QipianDeYishu/js/__init__.py
QipianDeYishu/js/epub.js
QipianDeYishu/js/epub.min.js
QipianDeYishu/js/epub.min.map
QipianDeYishu/js/hooks.min.js
QipianDeYishu/js/hooks.min.map
QipianDeYishu/js/reader.js
QipianDeYishu/js/reader.js.map
QipianDeYishu/js/reader.min.js
QipianDeYishu/js/reader.min.map
QipianDeYishu/js/hooks/__init__.py
QipianDeYishu/js/hooks/extensions/__init__.py
QipianDeYishu/js/hooks/extensions/highlight.js
QipianDeYishu/js/libs/__init__.py
QipianDeYishu/js/libs/jquery.min.js
QipianDeYishu/js/libs/localforage.min.js
QipianDeYishu/js/libs/screenfull.js
QipianDeYishu/js/libs/screenfull.min.js
QipianDeYishu/js/libs/zip.min.js
QipianDeYishu/js/plugins/__init__.py
QipianDeYishu/js/plugins/hypothesis.js
QipianDeYishu/js/plugins/search.js
qipian_de_yishu-2024.3.1.0.dist-info/METADATA
qipian_de_yishu-2024.3.1.0.dist-info/WHEEL
qipian_de_yishu-2024.3.1.0.dist-info/entry_points.txt
qipian_de_yishu-2024.3.1.0.dist-info/top_level.txt
qipian_de_yishu-2024.3.1.0.dist-info/RECORD
